package android_src.mms.transaction;

import android.content.Context;
import android.net.Uri;

public class ReadRecTransaction extends Transaction
{
  private final Uri a;

  public ReadRecTransaction(Context paramContext, int paramInt, TransactionSettings paramTransactionSettings, String paramString)
  {
    super(paramContext, paramInt, paramTransactionSettings);
    this.a = Uri.parse(paramString);
    this.c = paramString;
    a(RetryScheduler.a(paramContext));
  }

  // ERROR //
  public void a()
  {
    // Byte code:
    //   0: aload_0
    //   1: getfield 42	android_src/mms/transaction/ReadRecTransaction:b	Landroid/content/Context;
    //   4: invokestatic 47	android_src/mms/pdu/PduPersister:a	(Landroid/content/Context;)Landroid_src/mms/pdu/PduPersister;
    //   7: astore_1
    //   8: aload_1
    //   9: aload_0
    //   10: getfield 19	android_src/mms/transaction/ReadRecTransaction:a	Landroid/net/Uri;
    //   13: invokevirtual 50	android_src/mms/pdu/PduPersister:a	(Landroid/net/Uri;)Landroid_src/mms/pdu/GenericPdu;
    //   16: checkcast 52	android_src/mms/pdu/ReadRecInd
    //   19: astore 6
    //   21: aload 6
    //   23: new 54	android_src/mms/pdu/EncodedStringValue
    //   26: dup
    //   27: aload_0
    //   28: getfield 42	android_src/mms/transaction/ReadRecTransaction:b	Landroid/content/Context;
    //   31: invokestatic 59	android_src/mms/ui/MessageUtils:a	(Landroid/content/Context;)Ljava/lang/String;
    //   34: invokespecial 62	android_src/mms/pdu/EncodedStringValue:<init>	(Ljava/lang/String;)V
    //   37: invokevirtual 65	android_src/mms/pdu/ReadRecInd:a	(Landroid_src/mms/pdu/EncodedStringValue;)V
    //   40: aload_0
    //   41: new 67	android_src/mms/pdu/PduComposer
    //   44: dup
    //   45: aload_0
    //   46: getfield 42	android_src/mms/transaction/ReadRecTransaction:b	Landroid/content/Context;
    //   49: aload 6
    //   51: invokespecial 70	android_src/mms/pdu/PduComposer:<init>	(Landroid/content/Context;Landroid_src/mms/pdu/GenericPdu;)V
    //   54: invokevirtual 73	android_src/mms/pdu/PduComposer:a	()[B
    //   57: invokevirtual 76	android_src/mms/transaction/ReadRecTransaction:a	([B)[B
    //   60: pop
    //   61: aload_1
    //   62: aload_0
    //   63: getfield 19	android_src/mms/transaction/ReadRecTransaction:a	Landroid/net/Uri;
    //   66: getstatic 79	android_src/provider/Telephony$Mms$Sent:a	Landroid/net/Uri;
    //   69: invokevirtual 82	android_src/mms/pdu/PduPersister:a	(Landroid/net/Uri;Landroid/net/Uri;)Landroid/net/Uri;
    //   72: astore 8
    //   74: aload_0
    //   75: getfield 86	android_src/mms/transaction/ReadRecTransaction:d	Landroid_src/mms/transaction/TransactionState;
    //   78: iconst_1
    //   79: invokevirtual 91	android_src/mms/transaction/TransactionState:a	(I)V
    //   82: aload_0
    //   83: getfield 86	android_src/mms/transaction/ReadRecTransaction:d	Landroid_src/mms/transaction/TransactionState;
    //   86: aload 8
    //   88: invokevirtual 94	android_src/mms/transaction/TransactionState:a	(Landroid/net/Uri;)V
    //   91: aload_0
    //   92: getfield 86	android_src/mms/transaction/ReadRecTransaction:d	Landroid_src/mms/transaction/TransactionState;
    //   95: invokevirtual 97	android_src/mms/transaction/TransactionState:a	()I
    //   98: iconst_1
    //   99: if_icmpeq +22 -> 121
    //   102: aload_0
    //   103: getfield 86	android_src/mms/transaction/ReadRecTransaction:d	Landroid_src/mms/transaction/TransactionState;
    //   106: iconst_2
    //   107: invokevirtual 91	android_src/mms/transaction/TransactionState:a	(I)V
    //   110: aload_0
    //   111: getfield 86	android_src/mms/transaction/ReadRecTransaction:d	Landroid_src/mms/transaction/TransactionState;
    //   114: aload_0
    //   115: getfield 19	android_src/mms/transaction/ReadRecTransaction:a	Landroid/net/Uri;
    //   118: invokevirtual 94	android_src/mms/transaction/TransactionState:a	(Landroid/net/Uri;)V
    //   121: aload_0
    //   122: invokevirtual 99	android_src/mms/transaction/ReadRecTransaction:c	()V
    //   125: return
    //   126: astore 5
    //   128: aload_0
    //   129: getfield 86	android_src/mms/transaction/ReadRecTransaction:d	Landroid_src/mms/transaction/TransactionState;
    //   132: invokevirtual 97	android_src/mms/transaction/TransactionState:a	()I
    //   135: iconst_1
    //   136: if_icmpeq +22 -> 158
    //   139: aload_0
    //   140: getfield 86	android_src/mms/transaction/ReadRecTransaction:d	Landroid_src/mms/transaction/TransactionState;
    //   143: iconst_2
    //   144: invokevirtual 91	android_src/mms/transaction/TransactionState:a	(I)V
    //   147: aload_0
    //   148: getfield 86	android_src/mms/transaction/ReadRecTransaction:d	Landroid_src/mms/transaction/TransactionState;
    //   151: aload_0
    //   152: getfield 19	android_src/mms/transaction/ReadRecTransaction:a	Landroid/net/Uri;
    //   155: invokevirtual 94	android_src/mms/transaction/TransactionState:a	(Landroid/net/Uri;)V
    //   158: aload_0
    //   159: invokevirtual 99	android_src/mms/transaction/ReadRecTransaction:c	()V
    //   162: goto -37 -> 125
    //   165: astore 4
    //   167: aload_0
    //   168: getfield 86	android_src/mms/transaction/ReadRecTransaction:d	Landroid_src/mms/transaction/TransactionState;
    //   171: invokevirtual 97	android_src/mms/transaction/TransactionState:a	()I
    //   174: iconst_1
    //   175: if_icmpeq +22 -> 197
    //   178: aload_0
    //   179: getfield 86	android_src/mms/transaction/ReadRecTransaction:d	Landroid_src/mms/transaction/TransactionState;
    //   182: iconst_2
    //   183: invokevirtual 91	android_src/mms/transaction/TransactionState:a	(I)V
    //   186: aload_0
    //   187: getfield 86	android_src/mms/transaction/ReadRecTransaction:d	Landroid_src/mms/transaction/TransactionState;
    //   190: aload_0
    //   191: getfield 19	android_src/mms/transaction/ReadRecTransaction:a	Landroid/net/Uri;
    //   194: invokevirtual 94	android_src/mms/transaction/TransactionState:a	(Landroid/net/Uri;)V
    //   197: aload_0
    //   198: invokevirtual 99	android_src/mms/transaction/ReadRecTransaction:c	()V
    //   201: goto -76 -> 125
    //   204: astore_3
    //   205: aload_0
    //   206: getfield 86	android_src/mms/transaction/ReadRecTransaction:d	Landroid_src/mms/transaction/TransactionState;
    //   209: invokevirtual 97	android_src/mms/transaction/TransactionState:a	()I
    //   212: iconst_1
    //   213: if_icmpeq +22 -> 235
    //   216: aload_0
    //   217: getfield 86	android_src/mms/transaction/ReadRecTransaction:d	Landroid_src/mms/transaction/TransactionState;
    //   220: iconst_2
    //   221: invokevirtual 91	android_src/mms/transaction/TransactionState:a	(I)V
    //   224: aload_0
    //   225: getfield 86	android_src/mms/transaction/ReadRecTransaction:d	Landroid_src/mms/transaction/TransactionState;
    //   228: aload_0
    //   229: getfield 19	android_src/mms/transaction/ReadRecTransaction:a	Landroid/net/Uri;
    //   232: invokevirtual 94	android_src/mms/transaction/TransactionState:a	(Landroid/net/Uri;)V
    //   235: aload_0
    //   236: invokevirtual 99	android_src/mms/transaction/ReadRecTransaction:c	()V
    //   239: goto -114 -> 125
    //   242: astore_2
    //   243: aload_0
    //   244: getfield 86	android_src/mms/transaction/ReadRecTransaction:d	Landroid_src/mms/transaction/TransactionState;
    //   247: invokevirtual 97	android_src/mms/transaction/TransactionState:a	()I
    //   250: iconst_1
    //   251: if_icmpeq +22 -> 273
    //   254: aload_0
    //   255: getfield 86	android_src/mms/transaction/ReadRecTransaction:d	Landroid_src/mms/transaction/TransactionState;
    //   258: iconst_2
    //   259: invokevirtual 91	android_src/mms/transaction/TransactionState:a	(I)V
    //   262: aload_0
    //   263: getfield 86	android_src/mms/transaction/ReadRecTransaction:d	Landroid_src/mms/transaction/TransactionState;
    //   266: aload_0
    //   267: getfield 19	android_src/mms/transaction/ReadRecTransaction:a	Landroid/net/Uri;
    //   270: invokevirtual 94	android_src/mms/transaction/TransactionState:a	(Landroid/net/Uri;)V
    //   273: aload_0
    //   274: invokevirtual 99	android_src/mms/transaction/ReadRecTransaction:c	()V
    //   277: aload_2
    //   278: athrow
    //
    // Exception table:
    //   from	to	target	type
    //   8	91	126	java/io/IOException
    //   8	91	165	android_src/mms/MmsException
    //   8	91	204	java/lang/RuntimeException
    //   8	91	242	finally
  }

  public int b()
  {
    return 3;
  }
}

/* Location:           /data1/software/jd-gui/com.facebook.katana_2.0_liqucn.com-dex2jar.jar
 * Qualified Name:     android_src.mms.transaction.ReadRecTransaction
 * JD-Core Version:    0.6.0
 */