package com.facebook.orca.common.names;

import android.text.TextUtils;
import java.text.Collator;
import java.util.ArrayList;
import java.util.Locale;

public class HanziToPinyin
{
  private static final Class<?> a = HanziToPinyin.class;
  private static final char[] b = { 21526, 21710, 23433, -32594, 20985, 20843, 25520, 25203, -28506, 21241, -27070, 22868, 20283, 30336, 30765, 28780, 24971, 27715, 20907, 30326, 23788, 22163, 20594, 21442, 20179, 25761, 20874, 23934, 22092, 25184, 25286, -28737, 20261, 25220, -28826, 25275, -27081, 21507, 20805, 25277, 20986, 25611, 24027, 20997, 21561, 26110, -29164, 21618, 20174, 20945, 31895, 27718, 23828, -28504, 25619, 21649, 21574, 20025, 24403, 20992, 24692, 25189, 28783, 20222, 22002, 25921, 20993, 29241, 19969, 19999, 19996, 21562, 21090, -32751, 22422, 21544, 22810, 22968, 22848, -26715, -32756, 21457, 24070, 21274, -26402, 20998, 20016, -30331, 20175, 22458, 32017, 22827, 29476, 26094, 20357, 24178, 20872, 30347, 25096, 32473, 26681, 25583, 21948, 22000, 24037, 21246, 20272, -25031, 20054, 20851, 20809, 24402, 20008, -29900, 21593, 22926, 21645, 20292, 22831, -31968, -29757, -24878, 25323, 20136, 21503, -24767, 20046, -32079, 24576, 27426, 24031, 28784, 26127, 21529, 19980, 21152, 25099, 27743, -32131, -27082, 24062, 22357, 20866, 20009, 20965, 23010, 22104, 20891, 21652, 24320, -27762, 24572, 23611, 21308, -32626, 21157, 31354, 25248, 25181, 22840, -31569, 23485, 21281, 20111, 22372, 25193, 25289, 20358, 20848, 21879, 25438, 20162, -26889, -32457, 26865, 26974, 21774, 20457, 23294, -32145, -29059, 22483, 21432, 25294, 28316, -24679, 23044, 22108, 23402, 25249, -26575, 22920, 22475, -26465, 29284, 29483, 21573, -27160, 27667, 21674, 23424, 21941, 20060, 27665, 21517, -29652, 25720, 29279, 27597, 25295, -32439, 22241, 22228, 23404, -29769, 23070, 23273, -32515, -27984, 25288, 23064, -25057, 25423, 22236, 23425, 22942, 20892, 32698, 22900, 22907, -24895, -28467, 22114, -29772, 22929, 25293, 30469, 27768, 25243, 21624, 21943, 21257, 20086, 29255, 21117, 27669, 23000, 20050, -27509, 21078, 20166, 19971, 25488, 21315, 21595, 24708, 20999, 20146, -26799, 23430, 29911, 21306, 23761, 28820, 22795, 21605, 31331, -31909, 24825, 20154, 25172, 26085, 25102, 21433, -28518, 22567, 26741, -27152, 25404, 20200, 27618, 19977, 26706, 25531, -32142, 26862, 20711, 26432, 31579, 23665, 20260, 24368, 22882, 30003, 21319, 23608, 21454, 20070, 21047, -30608, -27159, 21452, -29695, 21550, -29708, 21430, 24554, 20929, -32049, 29435, 22794, 23385, 21766, 20182, 23393, 22349, 27748, 22834, 24529, -32337, 21076, 22825, 26091, 24599, 21381, 28853, 20599, 20984, 28237, 25512, 21534, -29780, 21176, 27498, 24367, 23587, 21361, 26167, 32705, 25373, 20044, 22805, 21623, 20185, 20065, 28785, 20123, 24515, 20852, 20982, 20241, 25100, 21509, 30134, 28709, 20011, 21693, 22830, 24186, 20539, 19968, 20058, 24212, 21815, 20323, 20248, 32417, 22246, 26352, -31616, 24064, 28797, 20802, 29250, 20654, 21867, -25503, 24590, 26365, 21522, 25434, 27838, 24352, 20299, -30969, -29410, -24850, 20043, 20013, 24030, 26417, 25235, 25341, 19987, 22918, -26951, 23442, 21331, 20180, 23447, -28487, 31199, 21143, 22010, 23562, 26152 };
  private static final byte[][] c = { { 65, 0, 0, 0, 0, 0 }, { 65, 73, 0, 0, 0, 0 }, { 65, 78, 0, 0, 0, 0 }, { 65, 78, 71, 0, 0, 0 }, { 65, 79, 0, 0, 0, 0 }, { 66, 65, 0, 0, 0, 0 }, { 66, 65, 73, 0, 0, 0 }, { 66, 65, 78, 0, 0, 0 }, { 66, 65, 78, 71, 0, 0 }, { 66, 65, 79, 0, 0, 0 }, { 66, 69, 73, 0, 0, 0 }, { 66, 69, 78, 0, 0, 0 }, { 66, 69, 78, 71, 0, 0 }, { 66, 73, 0, 0, 0, 0 }, { 66, 73, 65, 78, 0, 0 }, { 66, 73, 65, 79, 0, 0 }, { 66, 73, 69, 0, 0, 0 }, { 66, 73, 78, 0, 0, 0 }, { 66, 73, 78, 71, 0, 0 }, { 66, 79, 0, 0, 0, 0 }, { 66, 85, 0, 0, 0, 0 }, { 67, 65, 0, 0, 0, 0 }, { 67, 65, 73, 0, 0, 0 }, { 67, 65, 78, 0, 0, 0 }, { 67, 65, 78, 71, 0, 0 }, { 67, 65, 79, 0, 0, 0 }, { 67, 69, 0, 0, 0, 0 }, { 67, 69, 78, 0, 0, 0 }, { 67, 69, 78, 71, 0, 0 }, { 67, 72, 65, 0, 0, 0 }, { 67, 72, 65, 73, 0, 0 }, { 67, 72, 65, 78, 0, 0 }, { 67, 72, 65, 78, 71, 0 }, { 67, 72, 65, 79, 0, 0 }, { 67, 72, 69, 0, 0, 0 }, { 67, 72, 69, 78, 0, 0 }, { 67, 72, 69, 78, 71, 0 }, { 67, 72, 73, 0, 0, 0 }, { 67, 72, 79, 78, 71, 0 }, { 67, 72, 79, 85, 0, 0 }, { 67, 72, 85, 0, 0, 0 }, { 67, 72, 85, 65, 73, 0 }, { 67, 72, 85, 65, 78, 0 }, { 67, 72, 85, 65, 78, 71 }, { 67, 72, 85, 73, 0, 0 }, { 67, 72, 85, 78, 0, 0 }, { 67, 72, 85, 79, 0, 0 }, { 67, 73, 0, 0, 0, 0 }, { 67, 79, 78, 71, 0, 0 }, { 67, 79, 85, 0, 0, 0 }, { 67, 85, 0, 0, 0, 0 }, { 67, 85, 65, 78, 0, 0 }, { 67, 85, 73, 0, 0, 0 }, { 67, 85, 78, 0, 0, 0 }, { 67, 85, 79, 0, 0, 0 }, { 68, 65, 0, 0, 0, 0 }, { 68, 65, 73, 0, 0, 0 }, { 68, 65, 78, 0, 0, 0 }, { 68, 65, 78, 71, 0, 0 }, { 68, 65, 79, 0, 0, 0 }, { 68, 69, 0, 0, 0, 0 }, { 68, 69, 78, 0, 0, 0 }, { 68, 69, 78, 71, 0, 0 }, { 68, 73, 0, 0, 0, 0 }, { 68, 73, 65, 0, 0, 0 }, { 68, 73, 65, 78, 0, 0 }, { 68, 73, 65, 79, 0, 0 }, { 68, 73, 69, 0, 0, 0 }, { 68, 73, 78, 71, 0, 0 }, { 68, 73, 85, 0, 0, 0 }, { 68, 79, 78, 71, 0, 0 }, { 68, 79, 85, 0, 0, 0 }, { 68, 85, 0, 0, 0, 0 }, { 68, 85, 65, 78, 0, 0 }, { 68, 85, 73, 0, 0, 0 }, { 68, 85, 78, 0, 0, 0 }, { 68, 85, 79, 0, 0, 0 }, { 69, 0, 0, 0, 0, 0 }, { 69, 78, 0, 0, 0, 0 }, { 69, 78, 71, 0, 0, 0 }, { 69, 82, 0, 0, 0, 0 }, { 70, 65, 0, 0, 0, 0 }, { 70, 65, 78, 0, 0, 0 }, { 70, 65, 78, 71, 0, 0 }, { 70, 69, 73, 0, 0, 0 }, { 70, 69, 78, 0, 0, 0 }, { 70, 69, 78, 71, 0, 0 }, { 70, 73, 65, 79, 0, 0 }, { 70, 79, 0, 0, 0, 0 }, { 70, 85, 0, 0, 0, 0 }, { 70, 79, 85, 0, 0, 0 }, { 70, 85, 0, 0, 0, 0 }, { 71, 85, 73, 0, 0, 0 }, { 71, 65, 0, 0, 0, 0 }, { 71, 65, 73, 0, 0, 0 }, { 71, 65, 78, 0, 0, 0 }, { 71, 65, 78, 71, 0, 0 }, { 71, 65, 79, 0, 0, 0 }, { 71, 69, 0, 0, 0, 0 }, { 71, 69, 73, 0, 0, 0 }, { 71, 69, 78, 0, 0, 0 }, { 71, 69, 78, 71, 0, 0 }, { 74, 73, 69, 0, 0, 0 }, { 71, 69, 0, 0, 0, 0 }, { 71, 79, 78, 71, 0, 0 }, { 71, 79, 85, 0, 0, 0 }, { 71, 85, 0, 0, 0, 0 }, { 71, 85, 65, 0, 0, 0 }, { 71, 85, 65, 73, 0, 0 }, { 71, 85, 65, 78, 0, 0 }, { 71, 85, 65, 78, 71, 0 }, { 71, 85, 73, 0, 0, 0 }, { 71, 85, 78, 0, 0, 0 }, { 71, 85, 65, 78, 0, 0 }, { 71, 85, 79, 0, 0, 0 }, { 72, 65, 0, 0, 0, 0 }, { 72, 65, 73, 0, 0, 0 }, { 72, 65, 78, 0, 0, 0 }, { 72, 65, 78, 71, 0, 0 }, { 72, 65, 79, 0, 0, 0 }, { 72, 69, 0, 0, 0, 0 }, { 72, 69, 73, 0, 0, 0 }, { 72, 69, 78, 0, 0, 0 }, { 72, 69, 78, 71, 0, 0 }, { 72, 79, 78, 71, 0, 0 }, { 72, 79, 85, 0, 0, 0 }, { 72, 85, 0, 0, 0, 0 }, { 72, 85, 65, 0, 0, 0 }, { 72, 85, 65, 73, 0, 0 }, { 72, 85, 65, 78, 0, 0 }, { 72, 85, 65, 78, 71, 0 }, { 72, 85, 73, 0, 0, 0 }, { 72, 85, 78, 0, 0, 0 }, { 72, 85, 79, 0, 0, 0 }, { 74, 73, 0, 0, 0, 0 }, { 74, 73, 65, 0, 0, 0 }, { 74, 73, 65, 78, 0, 0 }, { 74, 73, 65, 78, 71, 0 }, { 74, 73, 65, 79, 0, 0 }, { 74, 73, 69, 0, 0, 0 }, { 74, 73, 78, 0, 0, 0 }, { 74, 73, 78, 71, 0, 0 }, { 74, 73, 79, 78, 71, 0 }, { 74, 73, 85, 0, 0, 0 }, { 74, 85, 0, 0, 0, 0 }, { 74, 85, 65, 78, 0, 0 }, { 74, 85, 69, 0, 0, 0 }, { 74, 85, 78, 0, 0, 0 }, { 75, 65, 0, 0, 0, 0 }, { 75, 65, 73, 0, 0, 0 }, { 75, 65, 78, 0, 0, 0 }, { 75, 65, 78, 71, 0, 0 }, { 75, 65, 79, 0, 0, 0 }, { 75, 69, 0, 0, 0, 0 }, { 75, 69, 78, 0, 0, 0 }, { 75, 69, 78, 71, 0, 0 }, { 75, 79, 78, 71, 0, 0 }, { 75, 79, 85, 0, 0, 0 }, { 75, 85, 0, 0, 0, 0 }, { 75, 85, 65, 0, 0, 0 }, { 75, 85, 65, 73, 0, 0 }, { 75, 85, 65, 78, 0, 0 }, { 75, 85, 65, 78, 71, 0 }, { 75, 85, 73, 0, 0, 0 }, { 75, 85, 78, 0, 0, 0 }, { 75, 85, 79, 0, 0, 0 }, { 76, 65, 0, 0, 0, 0 }, { 76, 65, 73, 0, 0, 0 }, { 76, 65, 78, 0, 0, 0 }, { 76, 65, 78, 71, 0, 0 }, { 76, 65, 79, 0, 0, 0 }, { 76, 69, 0, 0, 0, 0 }, { 76, 69, 73, 0, 0, 0 }, { 76, 73, 0, 0, 0, 0 }, { 76, 73, 78, 71, 0, 0 }, { 76, 69, 78, 71, 0, 0 }, { 76, 73, 0, 0, 0, 0 }, { 76, 73, 65, 0, 0, 0 }, { 76, 73, 65, 78, 0, 0 }, { 76, 73, 65, 78, 71, 0 }, { 76, 73, 65, 79, 0, 0 }, { 76, 73, 69, 0, 0, 0 }, { 76, 73, 78, 0, 0, 0 }, { 76, 73, 78, 71, 0, 0 }, { 76, 73, 85, 0, 0, 0 }, { 76, 79, 78, 71, 0, 0 }, { 76, 79, 85, 0, 0, 0 }, { 76, 85, 0, 0, 0, 0 }, { 76, 85, 65, 78, 0, 0 }, { 76, 85, 78, 0, 0, 0 }, { 76, 85, 79, 0, 0, 0 }, { 77, 65, 0, 0, 0, 0 }, { 77, 65, 73, 0, 0, 0 }, { 77, 65, 78, 0, 0, 0 }, { 77, 65, 78, 71, 0, 0 }, { 77, 65, 79, 0, 0, 0 }, { 77, 69, 73, 0, 0, 0 }, { 77, 69, 78, 0, 0, 0 }, { 77, 69, 78, 71, 0, 0 }, { 77, 73, 0, 0, 0, 0 }, { 77, 73, 65, 78, 0, 0 }, { 77, 73, 65, 79, 0, 0 }, { 77, 73, 69, 0, 0, 0 }, { 77, 73, 78, 0, 0, 0 }, { 77, 73, 78, 71, 0, 0 }, { 77, 73, 85, 0, 0, 0 }, { 77, 79, 0, 0, 0, 0 }, { 77, 79, 85, 0, 0, 0 }, { 77, 85, 0, 0, 0, 0 }, { 78, 65, 0, 0, 0, 0 }, { 78, 65, 73, 0, 0, 0 }, { 78, 65, 78, 0, 0, 0 }, { 78, 65, 78, 71, 0, 0 }, { 78, 65, 79, 0, 0, 0 }, { 78, 69, 0, 0, 0, 0 }, { 78, 69, 73, 0, 0, 0 }, { 78, 69, 78, 0, 0, 0 }, { 78, 69, 78, 71, 0, 0 }, { 78, 73, 0, 0, 0, 0 }, { 78, 73, 65, 78, 0, 0 }, { 78, 73, 65, 78, 71, 0 }, { 78, 73, 65, 79, 0, 0 }, { 78, 73, 69, 0, 0, 0 }, { 78, 73, 78, 0, 0, 0 }, { 78, 73, 78, 71, 0, 0 }, { 78, 73, 85, 0, 0, 0 }, { 78, 79, 78, 71, 0, 0 }, { 78, 79, 85, 0, 0, 0 }, { 78, 85, 0, 0, 0, 0 }, { 78, 85, 65, 78, 0, 0 }, { 78, 85, 78, 0, 0, 0 }, { 78, 85, 79, 0, 0, 0 }, { 79, 0, 0, 0, 0, 0 }, { 79, 85, 0, 0, 0, 0 }, { 80, 65, 0, 0, 0, 0 }, { 80, 65, 73, 0, 0, 0 }, { 80, 65, 78, 0, 0, 0 }, { 80, 65, 78, 71, 0, 0 }, { 80, 65, 79, 0, 0, 0 }, { 80, 69, 73, 0, 0, 0 }, { 80, 69, 78, 0, 0, 0 }, { 80, 69, 78, 71, 0, 0 }, { 80, 73, 0, 0, 0, 0 }, { 80, 73, 65, 78, 0, 0 }, { 80, 73, 65, 79, 0, 0 }, { 80, 73, 69, 0, 0, 0 }, { 80, 73, 78, 0, 0, 0 }, { 80, 73, 78, 71, 0, 0 }, { 80, 79, 0, 0, 0, 0 }, { 80, 79, 85, 0, 0, 0 }, { 80, 85, 0, 0, 0, 0 }, { 81, 73, 0, 0, 0, 0 }, { 81, 73, 65, 0, 0, 0 }, { 81, 73, 65, 78, 0, 0 }, { 81, 73, 65, 78, 71, 0 }, { 81, 73, 65, 79, 0, 0 }, { 81, 73, 69, 0, 0, 0 }, { 81, 73, 78, 0, 0, 0 }, { 81, 73, 78, 71, 0, 0 }, { 81, 73, 79, 78, 71, 0 }, { 81, 73, 85, 0, 0, 0 }, { 81, 85, 0, 0, 0, 0 }, { 81, 85, 65, 78, 0, 0 }, { 81, 85, 69, 0, 0, 0 }, { 81, 85, 78, 0, 0, 0 }, { 82, 65, 78, 0, 0, 0 }, { 82, 65, 78, 71, 0, 0 }, { 82, 65, 79, 0, 0, 0 }, { 82, 69, 0, 0, 0, 0 }, { 82, 69, 78, 0, 0, 0 }, { 82, 69, 78, 71, 0, 0 }, { 82, 73, 0, 0, 0, 0 }, { 82, 79, 78, 71, 0, 0 }, { 82, 79, 85, 0, 0, 0 }, { 82, 85, 0, 0, 0, 0 }, { 82, 85, 65, 78, 0, 0 }, { 82, 85, 73, 0, 0, 0 }, { 82, 85, 78, 0, 0, 0 }, { 82, 85, 79, 0, 0, 0 }, { 83, 65, 0, 0, 0, 0 }, { 83, 65, 73, 0, 0, 0 }, { 83, 65, 78, 0, 0, 0 }, { 83, 65, 78, 71, 0, 0 }, { 83, 65, 79, 0, 0, 0 }, { 83, 69, 0, 0, 0, 0 }, { 83, 69, 78, 0, 0, 0 }, { 83, 69, 78, 71, 0, 0 }, { 83, 72, 65, 0, 0, 0 }, { 83, 72, 65, 73, 0, 0 }, { 83, 72, 65, 78, 0, 0 }, { 83, 72, 65, 78, 71, 0 }, { 83, 72, 65, 79, 0, 0 }, { 83, 72, 69, 0, 0, 0 }, { 83, 72, 69, 78, 0, 0 }, { 83, 72, 69, 78, 71, 0 }, { 83, 72, 73, 0, 0, 0 }, { 83, 72, 79, 85, 0, 0 }, { 83, 72, 85, 0, 0, 0 }, { 83, 72, 85, 65, 0, 0 }, { 83, 72, 85, 65, 73, 0 }, { 83, 72, 85, 65, 78, 0 }, { 83, 72, 85, 65, 78, 71 }, { 83, 72, 85, 73, 0, 0 }, { 83, 72, 85, 78, 0, 0 }, { 83, 72, 85, 79, 0, 0 }, { 83, 73, 0, 0, 0, 0 }, { 83, 79, 78, 71, 0, 0 }, { 83, 79, 85, 0, 0, 0 }, { 83, 85, 0, 0, 0, 0 }, { 83, 85, 65, 78, 0, 0 }, { 83, 85, 73, 0, 0, 0 }, { 83, 85, 78, 0, 0, 0 }, { 83, 85, 79, 0, 0, 0 }, { 84, 65, 0, 0, 0, 0 }, { 84, 65, 73, 0, 0, 0 }, { 84, 65, 78, 0, 0, 0 }, { 84, 65, 78, 71, 0, 0 }, { 84, 65, 79, 0, 0, 0 }, { 84, 69, 0, 0, 0, 0 }, { 84, 69, 78, 71, 0, 0 }, { 84, 73, 0, 0, 0, 0 }, { 84, 73, 65, 78, 0, 0 }, { 84, 73, 65, 79, 0, 0 }, { 84, 73, 69, 0, 0, 0 }, { 84, 73, 78, 71, 0, 0 }, { 84, 79, 78, 71, 0, 0 }, { 84, 79, 85, 0, 0, 0 }, { 84, 85, 0, 0, 0, 0 }, { 84, 85, 65, 78, 0, 0 }, { 84, 85, 73, 0, 0, 0 }, { 84, 85, 78, 0, 0, 0 }, { 84, 85, 79, 0, 0, 0 }, { 87, 65, 0, 0, 0, 0 }, { 87, 65, 73, 0, 0, 0 }, { 87, 65, 78, 0, 0, 0 }, { 87, 65, 78, 71, 0, 0 }, { 87, 69, 73, 0, 0, 0 }, { 87, 69, 78, 0, 0, 0 }, { 87, 69, 78, 71, 0, 0 }, { 87, 79, 0, 0, 0, 0 }, { 87, 85, 0, 0, 0, 0 }, { 88, 73, 0, 0, 0, 0 }, { 88, 73, 65, 0, 0, 0 }, { 88, 73, 65, 78, 0, 0 }, { 88, 73, 65, 78, 71, 0 }, { 88, 73, 65, 79, 0, 0 }, { 88, 73, 69, 0, 0, 0 }, { 88, 73, 78, 0, 0, 0 }, { 88, 73, 78, 71, 0, 0 }, { 88, 73, 79, 78, 71, 0 }, { 88, 73, 85, 0, 0, 0 }, { 88, 85, 0, 0, 0, 0 }, { 88, 85, 65, 78, 0, 0 }, { 88, 85, 69, 0, 0, 0 }, { 88, 85, 78, 0, 0, 0 }, { 89, 65, 0, 0, 0, 0 }, { 89, 65, 78, 0, 0, 0 }, { 89, 65, 78, 71, 0, 0 }, { 89, 65, 79, 0, 0, 0 }, { 89, 69, 0, 0, 0, 0 }, { 89, 73, 0, 0, 0, 0 }, { 89, 73, 78, 0, 0, 0 }, { 89, 73, 78, 71, 0, 0 }, { 89, 79, 0, 0, 0, 0 }, { 89, 79, 78, 71, 0, 0 }, { 89, 79, 85, 0, 0, 0 }, { 89, 85, 0, 0, 0, 0 }, { 89, 85, 65, 78, 0, 0 }, { 89, 85, 69, 0, 0, 0 }, { 89, 85, 78, 0, 0, 0 }, { 90, 65, 0, 0, 0, 0 }, { 90, 65, 73, 0, 0, 0 }, { 90, 65, 78, 0, 0, 0 }, { 90, 65, 78, 71, 0, 0 }, { 90, 65, 79, 0, 0, 0 }, { 90, 69, 0, 0, 0, 0 }, { 90, 69, 73, 0, 0, 0 }, { 90, 69, 78, 0, 0, 0 }, { 90, 69, 78, 71, 0, 0 }, { 90, 72, 65, 0, 0, 0 }, { 90, 72, 65, 73, 0, 0 }, { 90, 72, 65, 78, 0, 0 }, { 90, 72, 65, 78, 71, 0 }, { 90, 72, 65, 79, 0, 0 }, { 90, 72, 69, 0, 0, 0 }, { 90, 72, 69, 78, 0, 0 }, { 90, 72, 69, 78, 71, 0 }, { 90, 72, 73, 0, 0, 0 }, { 90, 72, 79, 78, 71, 0 }, { 90, 72, 79, 85, 0, 0 }, { 90, 72, 85, 0, 0, 0 }, { 90, 72, 85, 65, 0, 0 }, { 90, 72, 85, 65, 73, 0 }, { 90, 72, 85, 65, 78, 0 }, { 90, 72, 85, 65, 78, 71 }, { 90, 72, 85, 73, 0, 0 }, { 90, 72, 85, 78, 0, 0 }, { 90, 72, 85, 79, 0, 0 }, { 90, 73, 0, 0, 0, 0 }, { 90, 79, 78, 71, 0, 0 }, { 90, 79, 85, 0, 0, 0 }, { 90, 85, 0, 0, 0, 0 }, { 90, 85, 65, 78, 0, 0 }, { 90, 85, 73, 0, 0, 0 }, { 90, 85, 78, 0, 0, 0 }, { 90, 85, 79, 0, 0, 0 } };
  private static final Collator d = Collator.getInstance(Locale.CHINA);
  private static HanziToPinyin e;
  private final boolean f;

  protected HanziToPinyin(boolean paramBoolean)
  {
    this.f = paramBoolean;
  }

  private HanziToPinyin.Token a(char paramChar)
  {
    int i = 0;
    HanziToPinyin.Token localToken1 = new HanziToPinyin.Token();
    String str1 = Character.toString(paramChar);
    localToken1.b = str1;
    int j = -1;
    HanziToPinyin.Token localToken2;
    if (paramChar < 'Ā')
    {
      localToken1.a = 1;
      localToken1.c = str1;
      localToken2 = localToken1;
    }
    int k;
    while (true)
    {
      return localToken2;
      if (paramChar < '㐀')
      {
        localToken1.a = 3;
        localToken1.c = str1;
        localToken2 = localToken1;
        continue;
      }
      k = d.compare(str1, "吖");
      if (k >= 0)
        break;
      localToken1.a = 3;
      localToken1.c = str1;
      localToken2 = localToken1;
    }
    label121: int i3;
    int i4;
    int i6;
    int i7;
    label158: int i1;
    int n;
    if (k == 0)
    {
      localToken1.a = 2;
      j = 0;
      localToken1.a = 2;
      if (j >= 0)
        break label375;
      int i2 = -1 + b.length;
      i3 = j;
      i4 = 0;
      int i5 = k;
      i6 = i2;
      i7 = i5;
      if (i4 > i6)
        break label364;
      i3 = (i4 + i6) / 2;
      String str2 = Character.toString(b[i3]);
      i7 = d.compare(str1, str2);
      if (i7 != 0)
        break label326;
      i1 = i7;
      n = i3;
    }
    while (true)
    {
      if (i1 < 0)
        n--;
      StringBuilder localStringBuilder = new StringBuilder();
      while (true)
        if ((i < c[n].length) && (c[n][i] != 0))
        {
          localStringBuilder.append((char)c[n][i]);
          i++;
          continue;
          k = d.compare(str1, "咗");
          if (k > 0)
          {
            localToken1.a = 3;
            localToken1.c = str1;
            localToken2 = localToken1;
            break;
          }
          if (k != 0)
            break label121;
          localToken1.a = 2;
          j = -1 + b.length;
          break label121;
          label326: if (i7 > 0)
          {
            i4 = i3 + 1;
            break label158;
          }
          i6 = i3 - 1;
          break label158;
        }
      localToken1.c = localStringBuilder.toString();
      localToken2 = localToken1;
      break;
      label364: i1 = i7;
      n = i3;
      continue;
      label375: int m = k;
      n = j;
      i1 = m;
    }
  }

  // ERROR //
  public static HanziToPinyin a()
  {
    // Byte code:
    //   0: iconst_0
    //   1: istore_0
    //   2: ldc 2
    //   4: monitorenter
    //   5: getstatic 518	com/facebook/orca/common/names/HanziToPinyin:e	Lcom/facebook/orca/common/names/HanziToPinyin;
    //   8: ifnull +13 -> 21
    //   11: getstatic 518	com/facebook/orca/common/names/HanziToPinyin:e	Lcom/facebook/orca/common/names/HanziToPinyin;
    //   14: astore_3
    //   15: ldc 2
    //   17: monitorexit
    //   18: goto +85 -> 103
    //   21: invokestatic 522	java/text/Collator:getAvailableLocales	()[Ljava/util/Locale;
    //   24: astore_2
    //   25: iload_0
    //   26: aload_2
    //   27: arraylength
    //   28: if_icmpge +48 -> 76
    //   31: aload_2
    //   32: iload_0
    //   33: aaload
    //   34: getstatic 465	java/util/Locale:CHINA	Ljava/util/Locale;
    //   37: invokevirtual 526	java/util/Locale:equals	(Ljava/lang/Object;)Z
    //   40: ifeq +30 -> 70
    //   43: new 2	com/facebook/orca/common/names/HanziToPinyin
    //   46: dup
    //   47: iconst_1
    //   48: invokespecial 528	com/facebook/orca/common/names/HanziToPinyin:<init>	(Z)V
    //   51: putstatic 518	com/facebook/orca/common/names/HanziToPinyin:e	Lcom/facebook/orca/common/names/HanziToPinyin;
    //   54: getstatic 518	com/facebook/orca/common/names/HanziToPinyin:e	Lcom/facebook/orca/common/names/HanziToPinyin;
    //   57: astore_3
    //   58: ldc 2
    //   60: monitorexit
    //   61: goto +42 -> 103
    //   64: astore_1
    //   65: ldc 2
    //   67: monitorexit
    //   68: aload_1
    //   69: athrow
    //   70: iinc 0 1
    //   73: goto -48 -> 25
    //   76: getstatic 21	com/facebook/orca/common/names/HanziToPinyin:a	Ljava/lang/Class;
    //   79: ldc_w 530
    //   82: invokestatic 535	com/facebook/orca/debug/BLog:d	(Ljava/lang/Class;Ljava/lang/String;)V
    //   85: new 2	com/facebook/orca/common/names/HanziToPinyin
    //   88: dup
    //   89: iconst_0
    //   90: invokespecial 528	com/facebook/orca/common/names/HanziToPinyin:<init>	(Z)V
    //   93: putstatic 518	com/facebook/orca/common/names/HanziToPinyin:e	Lcom/facebook/orca/common/names/HanziToPinyin;
    //   96: getstatic 518	com/facebook/orca/common/names/HanziToPinyin:e	Lcom/facebook/orca/common/names/HanziToPinyin;
    //   99: astore_3
    //   100: ldc 2
    //   102: monitorexit
    //   103: aload_3
    //   104: areturn
    //
    // Exception table:
    //   from	to	target	type
    //   5	68	64	finally
    //   76	103	64	finally
  }

  private void a(StringBuilder paramStringBuilder, ArrayList<HanziToPinyin.Token> paramArrayList, int paramInt)
  {
    String str = paramStringBuilder.toString();
    paramArrayList.add(new HanziToPinyin.Token(paramInt, str, str));
    paramStringBuilder.setLength(0);
  }

  public ArrayList<HanziToPinyin.Token> a(String paramString)
  {
    ArrayList localArrayList1 = new ArrayList();
    if ((!this.f) || (TextUtils.isEmpty(paramString)));
    for (ArrayList localArrayList2 = localArrayList1; ; localArrayList2 = localArrayList1)
    {
      return localArrayList2;
      int i = paramString.length();
      StringBuilder localStringBuilder = new StringBuilder();
      int j = 0;
      int k = 1;
      if (j < i)
      {
        int m = paramString.charAt(j);
        if (m == 32)
          if (localStringBuilder.length() > 0)
            a(localStringBuilder, localArrayList1, k);
        while (true)
        {
          j++;
          break;
          if (m < 256)
          {
            if ((k != 1) && (localStringBuilder.length() > 0))
              a(localStringBuilder, localArrayList1, k);
            localStringBuilder.append(m);
            k = 1;
            continue;
          }
          if (m < 13312)
          {
            if ((k != 3) && (localStringBuilder.length() > 0))
              a(localStringBuilder, localArrayList1, k);
            localStringBuilder.append(m);
            k = 3;
            continue;
          }
          HanziToPinyin.Token localToken = a(m);
          if (localToken.a == 2)
          {
            if (localStringBuilder.length() > 0)
              a(localStringBuilder, localArrayList1, k);
            localArrayList1.add(localToken);
            k = 2;
            continue;
          }
          if ((k != localToken.a) && (localStringBuilder.length() > 0))
            a(localStringBuilder, localArrayList1, k);
          k = localToken.a;
          localStringBuilder.append(m);
        }
      }
      if (localStringBuilder.length() <= 0)
        continue;
      a(localStringBuilder, localArrayList1, k);
    }
  }
}

/* Location:           /data1/software/jd-gui/com.facebook.katana_2.0_liqucn.com-dex2jar.jar
 * Qualified Name:     com.facebook.orca.common.names.HanziToPinyin
 * JD-Core Version:    0.6.0
 */